modelcards/__init__.py
modelcards/card_data.py
modelcards/cards.py
modelcards/modelcard_template.md
tests/__init__.py
tests/hub_fixtures.py
tests/test_card_data.py
tests/test_cards.py
modelcards-0.1.6.dist-info/METADATA
modelcards-0.1.6.dist-info/WHEEL
modelcards-0.1.6.dist-info/top_level.txt
modelcards-0.1.6.dist-info/RECORD
