Metadata-Version: 2.1
Name: modelcards
Version: 0.1.6
Summary: 📝 Utility to create, edit, and publish model cards on the Hugging Face Hub.
Home-page: UNKNOWN
Author: Nathan Raw
Author-email: naterawdata@gmail.com
License: MIT
Platform: UNKNOWN
Requires-Dist: huggingface-hub (>=0.8.1)
Requires-Dist: Jinja2
Requires-Dist: pyyaml (>=5.1)
